python_object_getter/__init__.py
python_object_getter/py.typed
python_object_getter-0.0.2.dist-info/LICENSE.txt
python_object_getter-0.0.2.dist-info/METADATA
python_object_getter-0.0.2.dist-info/WHEEL
python_object_getter-0.0.2.dist-info/top_level.txt
python_object_getter-0.0.2.dist-info/RECORD
