Metadata-Version: 2.1
Name: python-object-getter
Version: 0.0.2
Summary: Import something from a module, while mocking anything in its namespace.
Home-page: https://github.com/boromir674/python-object-getter
Download-URL: https://github.com/boromir674/python-object-getter/archive/v0.0.2.tar.gz
Author: Konstantinos Lampridis
Author-email: k.lampridis@hotmail.com
License: AGPLv3
Project-URL: Bug Tracker, https://github.com/python-object-getter/issues
Project-URL: CI: Github Actions, https://github.com/boromir674/python-object-getter/actions
Project-URL: Documentation, https://python-object-getter.readthedocs.io/
Project-URL: Source Code, https://github.com/boromir674/python-object-getter
Keywords: python package
Platform: Linux
Platform: Darwin
Classifier: Development Status :: 5 - Production/Stable
Classifier: Intended Audience :: Developers
Classifier: Intended Audience :: End Users/Desktop
Classifier: Intended Audience :: Science/Research
Classifier: License :: OSI Approved :: GNU Affero General Public License v3
Classifier: Natural Language :: English
Classifier: Operating System :: Unix
Classifier: Programming Language :: Python
Classifier: Programming Language :: Python :: 3.6
Classifier: Programming Language :: Python :: 3.7
Classifier: Programming Language :: Python :: 3.8
Classifier: Programming Language :: Python :: 3.9
Classifier: Programming Language :: Python :: 3.10
Classifier: Topic :: Software Development
Classifier: Topic :: Software Development :: Libraries :: Python Modules
Classifier: Topic :: System :: Software Distribution
Classifier: Typing :: Typed
Requires-Python: >=3.6
License-File: LICENSE.txt
Provides-Extra: docs
Requires-Dist: furo (>=2021.08.31) ; extra == 'docs'
Requires-Dist: sphinx (~=4.0) ; extra == 'docs'
Requires-Dist: sphinx-argparse-cli (>=1.5) ; extra == 'docs'
Requires-Dist: sphinx-autodoc-typehints (>=1.10) ; extra == 'docs'
Provides-Extra: test
Requires-Dist: pytest (>=6.2.4) ; extra == 'test'
Requires-Dist: pytest-cov (>=2.12) ; extra == 'test'
Requires-Dist: pytest-xdist (>=1.34) ; extra == 'test'
Provides-Extra: typing
Requires-Dist: mypy ; extra == 'typing'
